ibcp/__init__.py
ibcp/ibcp.py
ibcp-0.0.3.dist-info/licenses/LICENSE
ibcp-0.0.3.dist-info/METADATA
ibcp-0.0.3.dist-info/WHEEL
ibcp-0.0.3.dist-info/top_level.txt
ibcp-0.0.3.dist-info/RECORD
