Metadata-Version: 2.4
Name: ibcp
Version: 0.0.3
Summary: Python Wrapper for Interactive Brokers API
Home-page: https://github.com/matthewmoorcroft/ibcp
Author: Matt
Author-email: matt@example.com
Project-URL: Bug Tracker, https://github.com/matthewmoorcroft/ibcp/issues
Keywords: interactive brokers,api,trading
Classifier: Development Status :: 3 - Alpha
Classifier: Intended Audience :: Developers
Classifier: License :: OSI Approved :: BSD License
Classifier: Operating System :: OS Independent
Classifier: Programming Language :: Python :: 3
Classifier: Programming Language :: Python :: 3.8
Classifier: Programming Language :: Python :: 3.9
Classifier: Programming Language :: Python :: 3.10
Classifier: Programming Language :: Python :: 3.11
Requires-Python: >=3.6
License-File: LICENSE
Requires-Dist: requests
Requires-Dist: urllib3
Dynamic: license-file
